README.rst
setup.py
pylas/__init__.py
pylas/checking.py
pylas/compression.py
pylas/errors.py
pylas/evlrs.py
pylas/extradims.py
pylas/lasmmap.py
pylas/lasreader.py
pylas/lib.py
pylas/utils.py
pylas.egg-info/PKG-INFO
pylas.egg-info/SOURCES.txt
pylas.egg-info/dependency_links.txt
pylas.egg-info/not-zip-safe
pylas.egg-info/requires.txt
pylas.egg-info/top_level.txt
pylas/headers/__init__.py
pylas/headers/rawheader.py
pylas/lasdatas/__init__.py
pylas/lasdatas/base.py
pylas/lasdatas/las12.py
pylas/lasdatas/las14.py
pylas/point/__init__.py
pylas/point/dims.py
pylas/point/format.py
pylas/point/packing.py
pylas/point/record.py
pylas/vlrs/__init__.py
pylas/vlrs/geotiff.py
pylas/vlrs/known.py
pylas/vlrs/rawvlr.py
pylas/vlrs/vlrlist.py