Metadata-Version: 1.2
Name: pylas
Version: 0.3.4
Summary: Las/Laz reading and writing in python
Home-page: https://github.com/tmontaigu/pylas
Author: Thomas Montaigu
Author-email: thomas.montaigu@laposte.net
License: BSD 3-Clause
Keywords: las lidar
Platform: UNKNOWN
Requires-Python: >=3
